haiku_errors.py
haiku_errors-0.3.0.dist-info/DESCRIPTION.rst
haiku_errors-0.3.0.dist-info/METADATA
haiku_errors-0.3.0.dist-info/RECORD
haiku_errors-0.3.0.dist-info/WHEEL
haiku_errors-0.3.0.dist-info/metadata.json
haiku_errors-0.3.0.dist-info/top_level.txt
haiku_errors-0.3.0.dist-info/zip-safe
