Metadata-Version: 2.0
Name: haiku-errors
Version: 0.3.0
Summary: Haiku error messages for Python
Home-page: https://github.com/pylola/haiku-errors
Author: Michał Jaworski
Author-email: swistakm@gmail.com
License: BSD
Platform: UNKNOWN
Classifier: Development Status :: 4 - Beta
Classifier: Intended Audience :: Developers
Classifier: License :: OSI Approved :: BSD License
Classifier: Operating System :: OS Independent
Classifier: Programming Language :: Python
Classifier: Programming Language :: Python :: 2
Classifier: Programming Language :: Python :: 3
Classifier: Topic :: Software Development :: Bug Tracking
